go_utils/__init__.py
go_utils/_cli.py
go_utils/cleanup.py
go_utils/download.py
go_utils/geoenrich.py
go_utils/info.py
go_utils/lc.py
go_utils/mhm.py
go_utils/photo_download.py
go_utils/plot.py
go_utils-2021.61.dist-info/LICENSE
go_utils-2021.61.dist-info/METADATA
go_utils-2021.61.dist-info/WHEEL
go_utils-2021.61.dist-info/entry_points.txt
go_utils-2021.61.dist-info/top_level.txt
go_utils-2021.61.dist-info/zip-safe
go_utils-2021.61.dist-info/RECORD
