Metadata-Version: 2.1
Name: go-utils
Version: 2021.61
Summary: Utilities for interfacing with GLOBE Observer Data
Home-page: UNKNOWN
Author: IGES
Maintainer: Matteo Kimura, Prachi Ingle, Pratham Babaria
Maintainer-email: mateus.sakata@gmail.com, phna14@gmail.com, prathambabaria1@gmail.com
License: MIT License
Project-URL: Source Code, https://github.com/IGES-Geospatial/globe-observer-utils
Project-URL: Documentation, https://iges-geospatial.github.io/globe-observer-utils-docs/go_utils.html
Project-URL: Bug Tracker, https://github.com/IGES-Geospatial/globe-observer-utils/issues
Keywords: GlobeObserver GLOBE mosquito landcover
Platform: UNKNOWN
Classifier: Intended Audience :: Education
Classifier: Operating System :: OS Independent
Classifier: License :: OSI Approved :: MIT License
Classifier: Topic :: Scientific/Engineering :: GIS
Classifier: Intended Audience :: Science/Research
Classifier: Programming Language :: Python :: 3
Requires-Python: >=3.6
License-File: LICENSE
Requires-Dist: numpy (>=1.19.0)
Requires-Dist: pandas (>=1.1.5)
Requires-Dist: requests (>=2.23.0)
Requires-Dist: arcgis (>=1.8.4)
Requires-Dist: seaborn (>=0.11.1)
